content/__init__.py
demographics/__init__.py
emails/__init__.py
headers/__init__.py
inbox/__init__.py
rtfpinbox-1.5.1.dist-info/METADATA
rtfpinbox-1.5.1.dist-info/WHEEL
rtfpinbox-1.5.1.dist-info/top_level.txt
rtfpinbox-1.5.1.dist-info/RECORD
